README.rst
jira2vsts.py
setup.py
jira2vsts.egg-info/PKG-INFO
jira2vsts.egg-info/SOURCES.txt
jira2vsts.egg-info/dependency_links.txt
jira2vsts.egg-info/entry_points.txt
jira2vsts.egg-info/requires.txt
jira2vsts.egg-info/top_level.txt