Metadata-Version: 1.0
Name: jira2vsts
Version: 0.1.1
Summary: Synchronize Jira issues to VSTS (Azure Devops)
Home-page: UNKNOWN
Author: Mohamed Cherkaoui
Author-email: chermed@gmail.com
License: LGPL v3
Keywords: jira2vsts
Platform: UNKNOWN
